alibabacloud_qianzhou20211111/__init__.py
alibabacloud_qianzhou20211111/client.py
alibabacloud_qianzhou20211111/models.py
alibabacloud_qianzhou20211111-1.0.2.dist-info/LICENSE
alibabacloud_qianzhou20211111-1.0.2.dist-info/METADATA
alibabacloud_qianzhou20211111-1.0.2.dist-info/WHEEL
alibabacloud_qianzhou20211111-1.0.2.dist-info/top_level.txt
alibabacloud_qianzhou20211111-1.0.2.dist-info/RECORD
